essentials/__init__.py
essentials/cdn/__init__.py
essentials/conversation/__init__.py
essentials/file_ops/__init__.py
essentials/html/__init__.py
essentials/image_ops/__init__.py
essentials/logger_ops/__init__.py
essentials/network_ops/__init__.py
essentials/objects/__init__.py
essentials/run_data/__init__.py
essentials/search/__init__.py
essentials/search/text/__init__.py
essentials/socket_ops/__init__.py
essentials/socket_ops_v2/__init__.py
essentials/time_events/__init__.py
essentials/tokening/__init__.py
essentials/typing/__init__.py
MkNxGn_Essentials-0.1.40.6.dist-info/LICENSE
MkNxGn_Essentials-0.1.40.6.dist-info/METADATA
MkNxGn_Essentials-0.1.40.6.dist-info/WHEEL
MkNxGn_Essentials-0.1.40.6.dist-info/top_level.txt
MkNxGn_Essentials-0.1.40.6.dist-info/RECORD
