Metadata-Version: 2.1
Name: MkNxGn_Essentials
Version: 0.1.40.6
Summary: MkNxGn File Writing, Network Essentials and More - A lot more
Home-page: https://mknxgn.com/
Author: Mark Cartagena
Author-email: mark@mknxgn.com
Classifier: Programming Language :: Python :: 3
Classifier: License :: OSI Approved :: MIT License
Classifier: Operating System :: OS Independent
License-File: LICENSE
